djcron-0.0.7.dist-info/metadata.json
djcron-0.0.7.dist-info/METADATA
djcron-0.0.7.dist-info/WHEEL
djcron-0.0.7.dist-info/RECORD
djcron-0.0.7.dist-info/top_level.txt
djcron-0.0.7.dist-info/DESCRIPTION.rst
djcron/versions.py
djcron/__init__.py
