Metadata-Version: 2.0
Name: djcron
Version: 0.0.7
Summary: Distributed cron manager package
Home-page: https://github.com/djcron-project/djcron
Author: Miguel Ángel García
Author-email: miguelangel.garcia@gmail.com
License: Affero
Keywords: distributed cron
Platform: UNKNOWN
Classifier: Development Status :: 4 - Beta
Classifier: Programming Language :: Python :: 2.7
Classifier: Programming Language :: Python :: 3.2
Classifier: Programming Language :: Python :: 3.3
Classifier: Programming Language :: Python :: 3.4
Classifier: Environment :: Console
Classifier: Intended Audience :: Developers
Classifier: License :: OSI Approved :: GNU Affero General Public License v3
Classifier: Operating System :: OS Independent
Requires-Dist: djcron-server (>=0.0,<0.1)
Requires-Dist: djcron-agent (>=0.0,<0.1)
